{
  "classname": null,
  "name": null,
  "animation": {
    "classname": null,
    "name": "AnimationManager",
    "actionlist": []
  },
  "dataScale": 1,
  "designHeight": 1080,
  "designWidth": 1920,
  "textures": [],
  "texturesPng": [],
  "version": "1.6.0.0",
  "widgetTree": {
    "classname": "Panel",
    "name": null,
    "children": [
      {
        "classname": "ImageView",
        "name": null,
        "children": [
          {
            "classname": "ImageView",
            "name": null,
            "children": [],
            "options": {
              "__type": "ImageViewSurrogate:#EditorCommon.JsonModel.Component.GUI",
              "classname": "ImageView",
              "name": "Image_bg",
              "ZOrder": 0,
              "actiontag": 11845043,
              "anchorPointX": 0.5,
              "anchorPointY": 0.5,
              "classType": "CocoStudio.EngineAdapterWrap.CSImageView",
              "colorB": 255,
              "colorG": 255,
              "colorR": 255,
              "customProperty": "",
              "flipX": false,
              "flipY": false,
              "height": 310,
              "ignoreSize": false,
              "layoutParameter": null,
              "opacity": 255,
              "positionPercentX": 0,
              "positionPercentY": 0.115273774,
              "positionType": 0,
              "rotation": 0,
              "scaleX": 1,
              "scaleY": 1,
              "sizePercentX": 0.8843212,
              "sizePercentY": 0.44668588,
              "sizeType": 0,
              "tag": 1000684636,
              "touchAble": false,
              "useMergedTexture": false,
              "visible": true,
              "width": 925,
              "x": 0,
              "y": 80,
              "capInsetsHeight": 10,
              "capInsetsWidth": 10,
              "capInsetsX": 20,
              "capInsetsY": 20,
              "fileName": null,
              "fileNameData": {
                "path": "res_ui/qyq/common/commonKuang/xinxiTiao.png",
                "plistFile": "",
                "resourceType": 0
              },
              "scale9Enable": true,
              "scale9Height": 310,
              "scale9Width": 925
            }
          },
          {
            "classname": "ImageView",
            "name": null,
            "children": [],
            "options": {
              "__type": "ImageViewSurrogate:#EditorCommon.JsonModel.Component.GUI",
              "classname": "ImageView",
              "name": "title",
              "ZOrder": 0,
              "actiontag": 32912398,
              "anchorPointX": 0.5,
              "anchorPointY": 0.5,
              "classType": "CocoStudio.EngineAdapterWrap.CSImageView",
              "colorB": 255,
              "colorG": 255,
              "colorR": 255,
              "customProperty": "",
              "flipX": false,
              "flipY": false,
              "height": 50,
              "ignoreSize": true,
              "layoutParameter": null,
              "opacity": 255,
              "positionPercentX": 0.009560229,
              "positionPercentY": 0.389049,
              "positionType": 0,
              "rotation": 0,
              "scaleX": 1,
              "scaleY": 1,
              "sizePercentX": 0.142447412,
              "sizePercentY": 0.07204611,
              "sizeType": 0,
              "tag": 1000505185,
              "touchAble": false,
              "useMergedTexture": false,
              "visible": true,
              "width": 149,
              "x": 10,
              "y": 270,
              "capInsetsHeight": 1,
              "capInsetsWidth": 1,
              "capInsetsX": 0,
              "capInsetsY": 0,
              "fileName": null,
              "fileNameData": {
                "path": "res_ui/qyq/huchimingdan/title_hcc.png",
                "plistFile": "",
                "resourceType": 0
              },
              "scale9Enable": false,
              "scale9Height": 50,
              "scale9Width": 149
            }
          },
          {
            "classname": "Button",
            "name": null,
            "children": [],
            "options": {
              "__type": "ButtonSurrogate:#EditorCommon.JsonModel.Component.GUI",
              "classname": "Button",
              "name": "close_btn",
              "ZOrder": 0,
              "actiontag": 9273238,
              "anchorPointX": 0.5,
              "anchorPointY": 0.5,
              "classType": "CocoStudio.EngineAdapterWrap.CSButton",
              "colorB": 255,
              "colorG": 255,
              "colorR": 255,
              "customProperty": "",
              "flipX": false,
              "flipY": false,
              "height": 73,
              "ignoreSize": true,
              "layoutParameter": null,
              "opacity": 255,
              "positionPercentX": 0.423518151,
              "positionPercentY": 0.381844372,
              "positionType": 0,
              "rotation": 0,
              "scaleX": 1,
              "scaleY": 1,
              "sizePercentX": 0.0640535355,
              "sizePercentY": 0.105187319,
              "sizeType": 0,
              "tag": 1000505186,
              "touchAble": true,
              "useMergedTexture": false,
              "visible": true,
              "width": 67,
              "x": 443,
              "y": 265,
              "capInsetsHeight": 1,
              "capInsetsWidth": 1,
              "capInsetsX": 0,
              "capInsetsY": 0,
              "disabled": null,
              "disabledData": {
                "path": null,
                "plistFile": null,
                "resourceType": 0
              },
              "fontName": "微软雅黑",
              "fontSize": 14,
              "fontType": 0,
              "normal": null,
              "normalData": {
                "path": "res_ui/qyq/common/commonButton/closeBtn.png",
                "plistFile": "",
                "resourceType": 0
              },
              "pressed": null,
              "pressedData": {
                "path": null,
                "plistFile": null,
                "resourceType": 0
              },
              "scale9Enable": false,
              "scale9Height": 73,
              "scale9Width": 67,
              "text": "",
              "textColorB": 255,
              "textColorG": 255,
              "textColorR": 255
            }
          },
          {
            "classname": "ScrollView",
            "name": null,
            "children": [
              {
                "classname": "ImageView",
                "name": null,
                "children": [
                  {
                    "classname": "Label",
                    "name": null,
                    "children": [],
                    "options": {
                      "__type": "LabelSurrogate:#EditorCommon.JsonModel.Component.GUI",
                      "classname": "Label",
                      "name": "Label_mutex1",
                      "ZOrder": 0,
                      "actiontag": 59252087,
                      "anchorPointX": 0.5,
                      "anchorPointY": 0.5,
                      "classType": "CocoStudio.EngineAdapterWrap.CSLabel",
                      "colorB": 22,
                      "colorG": 24,
                      "colorR": 111,
                      "customProperty": "",
                      "flipX": false,
                      "flipY": false,
                      "height": 67,
                      "ignoreSize": true,
                      "layoutParameter": null,
                      "opacity": 255,
                      "positionPercentX": 0,
                      "positionPercentY": 0,
                      "positionType": 0,
                      "rotation": 0,
                      "scaleX": 1,
                      "scaleY": 1,
                      "sizePercentX": 0.6,
                      "sizePercentY": 0.231034487,
                      "sizeType": 0,
                      "tag": 1000684638,
                      "touchAble": false,
                      "useMergedTexture": false,
                      "visible": true,
                      "width": 156,
                      "x": 0,
                      "y": 0,
                      "areaHeight": 0,
                      "areaWidth": 0,
                      "fontFile": null,
                      "fontName": "微软雅黑",
                      "fontSize": 52,
                      "hAlignment": 1,
                      "text": "互斥池",
                      "touchScaleEnable": false,
                      "vAlignment": 0
                    }
                  },
                  {
                    "classname": "Label",
                    "name": null,
                    "children": [],
                    "options": {
                      "__type": "LabelSurrogate:#EditorCommon.JsonModel.Component.GUI",
                      "classname": "Label",
                      "name": "Label_mutex",
                      "ZOrder": 0,
                      "actiontag": 12023263,
                      "anchorPointX": 0.5,
                      "anchorPointY": 0.5,
                      "classType": "CocoStudio.EngineAdapterWrap.CSLabel",
                      "colorB": 22,
                      "colorG": 24,
                      "colorR": 111,
                      "customProperty": "",
                      "flipX": false,
                      "flipY": false,
                      "height": 71,
                      "ignoreSize": true,
                      "layoutParameter": null,
                      "opacity": 255,
                      "positionPercentX": 0,
                      "positionPercentY": -0.2413793,
                      "positionType": 0,
                      "rotation": 0,
                      "scaleX": 1,
                      "scaleY": 1,
                      "sizePercentX": 0.246153846,
                      "sizePercentY": 0.244827583,
                      "sizeType": 0,
                      "tag": 1000684663,
                      "touchAble": false,
                      "useMergedTexture": false,
                      "visible": true,
                      "width": 64,
                      "x": 0,
                      "y": -70,
                      "areaHeight": 0,
                      "areaWidth": 0,
                      "fontFile": null,
                      "fontName": "微软雅黑",
                      "fontSize": 55,
                      "hAlignment": 1,
                      "text": "12",
                      "touchScaleEnable": false,
                      "vAlignment": 0
                    }
                  },
                  {
                    "classname": "Button",
                    "name": null,
                    "children": [],
                    "options": {
                      "__type": "ButtonSurrogate:#EditorCommon.JsonModel.Component.GUI",
                      "classname": "Button",
                      "name": "Button_remove",
                      "ZOrder": 0,
                      "actiontag": 55154142,
                      "anchorPointX": 0.5,
                      "anchorPointY": 0.5,
                      "classType": "CocoStudio.EngineAdapterWrap.CSButton",
                      "colorB": 255,
                      "colorG": 255,
                      "colorR": 255,
                      "customProperty": "",
                      "flipX": false,
                      "flipY": false,
                      "height": 57,
                      "ignoreSize": true,
                      "layoutParameter": null,
                      "opacity": 255,
                      "positionPercentX": 0.3846154,
                      "positionPercentY": 0.406896561,
                      "positionType": 0,
                      "rotation": 0,
                      "scaleX": 0.6,
                      "scaleY": 0.6,
                      "sizePercentX": 0.219230771,
                      "sizePercentY": 0.196551725,
                      "sizeType": 0,
                      "tag": 1000684661,
                      "touchAble": true,
                      "useMergedTexture": false,
                      "visible": true,
                      "width": 57,
                      "x": 100,
                      "y": 118,
                      "capInsetsHeight": 1,
                      "capInsetsWidth": 1,
                      "capInsetsX": 0,
                      "capInsetsY": 0,
                      "disabled": null,
                      "disabledData": {
                        "path": null,
                        "plistFile": null,
                        "resourceType": 0
                      },
                      "fontName": "微软雅黑",
                      "fontSize": 14,
                      "fontType": 0,
                      "normal": null,
                      "normalData": {
                        "path": "res_ui/qyq/zhanji/closeBtn.png",
                        "plistFile": "",
                        "resourceType": 0
                      },
                      "pressed": null,
                      "pressedData": {
                        "path": null,
                        "plistFile": null,
                        "resourceType": 0
                      },
                      "scale9Enable": false,
                      "scale9Height": 57,
                      "scale9Width": 57,
                      "text": "",
                      "textColorB": 255,
                      "textColorG": 255,
                      "textColorR": 255
                    }
                  },
                  {
                    "classname": "Label",
                    "name": null,
                    "children": [],
                    "options": {
                      "__type": "LabelSurrogate:#EditorCommon.JsonModel.Component.GUI",
                      "classname": "Label",
                      "name": "Label_num",
                      "ZOrder": 0,
                      "actiontag": 60795339,
                      "anchorPointX": 0,
                      "anchorPointY": 0.5,
                      "classType": "CocoStudio.EngineAdapterWrap.CSLabel",
                      "colorB": 22,
                      "colorG": 24,
                      "colorR": 111,
                      "customProperty": "",
                      "flipX": false,
                      "flipY": false,
                      "height": 52,
                      "ignoreSize": true,
                      "layoutParameter": null,
                      "opacity": 255,
                      "positionPercentX": -0.430769235,
                      "positionPercentY": 0.382758617,
                      "positionType": 0,
                      "rotation": 0,
                      "scaleX": 1,
                      "scaleY": 1,
                      "sizePercentX": 0.176923081,
                      "sizePercentY": 0.179310352,
                      "sizeType": 0,
                      "tag": 1000684665,
                      "touchAble": false,
                      "useMergedTexture": false,
                      "visible": true,
                      "width": 46,
                      "x": -112,
                      "y": 111,
                      "areaHeight": 0,
                      "areaWidth": 0,
                      "fontFile": null,
                      "fontName": "微软雅黑",
                      "fontSize": 40,
                      "hAlignment": 1,
                      "text": "12",
                      "touchScaleEnable": false,
                      "vAlignment": 0
                    }
                  }
                ],
                "options": {
                  "__type": "ImageViewSurrogate:#EditorCommon.JsonModel.Component.GUI",
                  "classname": "ImageView",
                  "name": "Image_mutex",
                  "ZOrder": 0,
                  "actiontag": 49772057,
                  "anchorPointX": 0.5,
                  "anchorPointY": 0.5,
                  "classType": "CocoStudio.EngineAdapterWrap.CSImageView",
                  "colorB": 255,
                  "colorG": 255,
                  "colorR": 255,
                  "customProperty": "",
                  "flipX": false,
                  "flipY": false,
                  "height": 290,
                  "ignoreSize": false,
                  "layoutParameter": null,
                  "opacity": 255,
                  "positionPercentX": 0.164324328,
                  "positionPercentY": 0.822580636,
                  "positionType": 0,
                  "rotation": 0,
                  "scaleX": 1,
                  "scaleY": 1,
                  "sizePercentX": 0.28108108,
                  "sizePercentY": 0.9354839,
                  "sizeType": 0,
                  "tag": 1000684637,
                  "touchAble": true,
                  "useMergedTexture": false,
                  "visible": true,
                  "width": 260,
                  "x": 152,
                  "y": 255,
                  "capInsetsHeight": 10,
                  "capInsetsWidth": 60,
                  "capInsetsX": 10,
                  "capInsetsY": 10,
                  "fileName": null,
                  "fileNameData": {
                    "path": "res_ui/qyq/wanfa/pxBtnDi.png",
                    "plistFile": "",
                    "resourceType": 0
                  },
                  "scale9Enable": true,
                  "scale9Height": 290,
                  "scale9Width": 260
                }
              }
            ],
            "options": {
              "__type": "ScrollViewSurrogate:#EditorCommon.JsonModel.Component.GUI",
              "classname": "ScrollView",
              "name": "ScrollView_m",
              "ZOrder": 0,
              "actiontag": 8552112,
              "anchorPointX": 0,
              "anchorPointY": 0,
              "classType": "CocoStudio.EngineAdapterWrap.CSScrollView",
              "colorB": 255,
              "colorG": 255,
              "colorR": 255,
              "customProperty": "",
              "flipX": false,
              "flipY": false,
              "height": 310,
              "ignoreSize": false,
              "layoutParameter": null,
              "opacity": 255,
              "positionPercentX": -0.43977055,
              "positionPercentY": -0.108069167,
              "positionType": 0,
              "rotation": 0,
              "scaleX": 1,
              "scaleY": 1,
              "sizePercentX": 0.8843212,
              "sizePercentY": 0.44668588,
              "sizeType": 0,
              "tag": 1000684658,
              "touchAble": true,
              "useMergedTexture": false,
              "visible": true,
              "width": 925,
              "x": -460,
              "y": -75,
              "backGroundImage": null,
              "backGroundImageData": null,
              "backGroundScale9Enable": false,
              "bgColorB": 100,
              "bgColorG": 150,
              "bgColorOpacity": 0,
              "bgColorR": 255,
              "bgEndColorB": 100,
              "bgEndColorG": 150,
              "bgEndColorR": 255,
              "bgStartColorB": 255,
              "bgStartColorG": 255,
              "bgStartColorR": 255,
              "bounceEnable": false,
              "capInsetsHeight": 1,
              "capInsetsWidth": 1,
              "capInsetsX": 0,
              "capInsetsY": 0,
              "clipAble": true,
              "colorType": 1,
              "direction": 2,
              "editorClipAble": true,
              "innerHeight": 408,
              "innerWidth": 1198,
              "layoutType": 0,
              "vectorX": 0,
              "vectorY": -0.5
            }
          },
          {
            "classname": "Button",
            "name": null,
            "children": [],
            "options": {
              "__type": "ButtonSurrogate:#EditorCommon.JsonModel.Component.GUI",
              "classname": "Button",
              "name": "Button_add",
              "ZOrder": 0,
              "actiontag": 36126309,
              "anchorPointX": 0.5,
              "anchorPointY": 0.5,
              "classType": "CocoStudio.EngineAdapterWrap.CSButton",
              "colorB": 255,
              "colorG": 255,
              "colorR": 255,
              "customProperty": "",
              "flipX": false,
              "flipY": false,
              "height": 101,
              "ignoreSize": true,
              "layoutParameter": null,
              "opacity": 255,
              "positionPercentX": -0.248565972,
              "positionPercentY": -0.3314121,
              "positionType": 0,
              "rotation": 0,
              "scaleX": 1,
              "scaleY": 1,
              "sizePercentX": 0.217973232,
              "sizePercentY": 0.145533144,
              "sizeType": 0,
              "tag": 1000684630,
              "touchAble": true,
              "useMergedTexture": false,
              "visible": true,
              "width": 228,
              "x": -260,
              "y": -230,
              "capInsetsHeight": 1,
              "capInsetsWidth": 1,
              "capInsetsX": 0,
              "capInsetsY": 0,
              "disabled": null,
              "disabledData": {
                "path": null,
                "plistFile": null,
                "resourceType": 0
              },
              "fontName": "微软雅黑",
              "fontSize": 14,
              "fontType": 0,
              "normal": null,
              "normalData": {
                "path": "res_ui/qyq/huchimingdan/addHuchichi.png",
                "plistFile": "",
                "resourceType": 0
              },
              "pressed": null,
              "pressedData": {
                "path": null,
                "plistFile": null,
                "resourceType": 0
              },
              "scale9Enable": false,
              "scale9Height": 101,
              "scale9Width": 228,
              "text": "",
              "textColorB": 255,
              "textColorG": 255,
              "textColorR": 255
            }
          },
          {
            "classname": "Button",
            "name": null,
            "children": [],
            "options": {
              "__type": "ButtonSurrogate:#EditorCommon.JsonModel.Component.GUI",
              "classname": "Button",
              "name": "Button_reduce",
              "ZOrder": 0,
              "actiontag": 3538826,
              "anchorPointX": 0.5,
              "anchorPointY": 0.5,
              "classType": "CocoStudio.EngineAdapterWrap.CSButton",
              "colorB": 255,
              "colorG": 255,
              "colorR": 255,
              "customProperty": "",
              "flipX": false,
              "flipY": false,
              "height": 101,
              "ignoreSize": true,
              "layoutParameter": null,
              "opacity": 255,
              "positionPercentX": 0.248565972,
              "positionPercentY": -0.3314121,
              "positionType": 0,
              "rotation": 0,
              "scaleX": 1,
              "scaleY": 1,
              "sizePercentX": 0.217973232,
              "sizePercentY": 0.145533144,
              "sizeType": 0,
              "tag": 1000684632,
              "touchAble": true,
              "useMergedTexture": false,
              "visible": true,
              "width": 228,
              "x": 260,
              "y": -230,
              "capInsetsHeight": 1,
              "capInsetsWidth": 1,
              "capInsetsX": 0,
              "capInsetsY": 0,
              "disabled": null,
              "disabledData": {
                "path": null,
                "plistFile": null,
                "resourceType": 0
              },
              "fontName": "微软雅黑",
              "fontSize": 14,
              "fontType": 0,
              "normal": null,
              "normalData": {
                "path": "res_ui/qyq/huchimingdan/deleteHuchichi.png",
                "plistFile": "",
                "resourceType": 0
              },
              "pressed": null,
              "pressedData": {
                "path": null,
                "plistFile": null,
                "resourceType": 0
              },
              "scale9Enable": false,
              "scale9Height": 101,
              "scale9Width": 228,
              "text": "",
              "textColorB": 255,
              "textColorG": 255,
              "textColorR": 255
            }
          },
          {
            "classname": "ImageView",
            "name": null,
            "children": [],
            "options": {
              "__type": "ImageViewSurrogate:#EditorCommon.JsonModel.Component.GUI",
              "classname": "ImageView",
              "name": "Image_input",
              "ZOrder": 0,
              "actiontag": 9056472,
              "anchorPointX": 0.5,
              "anchorPointY": 0.5,
              "classType": "CocoStudio.EngineAdapterWrap.CSImageView",
              "colorB": 255,
              "colorG": 255,
              "colorR": 255,
              "customProperty": "",
              "flipX": false,
              "flipY": false,
              "height": 70,
              "ignoreSize": false,
              "layoutParameter": null,
              "opacity": 255,
              "positionPercentX": 0,
              "positionPercentY": -0.18731989,
              "positionType": 0,
              "rotation": 0,
              "scaleX": 1,
              "scaleY": 1,
              "sizePercentX": 0.374761,
              "sizePercentY": 0.100864552,
              "sizeType": 0,
              "tag": 1000684633,
              "touchAble": false,
              "useMergedTexture": false,
              "visible": true,
              "width": 392,
              "x": 0,
              "y": -130,
              "capInsetsHeight": 30,
              "capInsetsWidth": 400,
              "capInsetsX": 30,
              "capInsetsY": 30,
              "fileName": null,
              "fileNameData": {
                "path": "res_ui/qyq/common/commonKuang/inputBg.png",
                "plistFile": "",
                "resourceType": 0
              },
              "scale9Enable": true,
              "scale9Height": 70,
              "scale9Width": 392
            }
          },
          {
            "classname": "Button",
            "name": null,
            "children": [],
            "options": {
              "__type": "ButtonSurrogate:#EditorCommon.JsonModel.Component.GUI",
              "classname": "Button",
              "name": "Button_find",
              "ZOrder": 0,
              "actiontag": 35666258,
              "anchorPointX": 0.5,
              "anchorPointY": 0.5,
              "classType": "CocoStudio.EngineAdapterWrap.CSButton",
              "colorB": 255,
              "colorG": 255,
              "colorR": 255,
              "customProperty": "",
              "flipX": false,
              "flipY": false,
              "height": 77,
              "ignoreSize": true,
              "layoutParameter": null,
              "opacity": 255,
              "positionPercentX": 0.10038241,
              "positionPercentY": -0.18731989,
              "positionType": 0,
              "rotation": 0,
              "scaleX": 1,
              "scaleY": 1,
              "sizePercentX": 0.180688336,
              "sizePercentY": 0.110951006,
              "sizeType": 0,
              "tag": 1000684635,
              "touchAble": true,
              "useMergedTexture": false,
              "visible": true,
              "width": 189,
              "x": 105,
              "y": -130,
              "capInsetsHeight": 1,
              "capInsetsWidth": 1,
              "capInsetsX": 0,
              "capInsetsY": 0,
              "disabled": null,
              "disabledData": {
                "path": null,
                "plistFile": null,
                "resourceType": 0
              },
              "fontName": "微软雅黑",
              "fontSize": 14,
              "fontType": 0,
              "normal": null,
              "normalData": {
                "path": "res_ui/qyq/tongji/chaxun.png",
                "plistFile": "",
                "resourceType": 0
              },
              "pressed": null,
              "pressedData": {
                "path": null,
                "plistFile": null,
                "resourceType": 0
              },
              "scale9Enable": false,
              "scale9Height": 77,
              "scale9Width": 189,
              "text": "",
              "textColorB": 255,
              "textColorG": 255,
              "textColorR": 255
            }
          }
        ],
        "options": {
          "__type": "ImageViewSurrogate:#EditorCommon.JsonModel.Component.GUI",
          "classname": "ImageView",
          "name": "mainPopup",
          "ZOrder": 0,
          "actiontag": 2649692,
          "anchorPointX": 0.5,
          "anchorPointY": 0.5,
          "classType": "CocoStudio.EngineAdapterWrap.CSImageView",
          "colorB": 255,
          "colorG": 255,
          "colorR": 255,
          "customProperty": "",
          "flipX": false,
          "flipY": false,
          "height": 694,
          "ignoreSize": true,
          "layoutParameter": null,
          "opacity": 255,
          "positionPercentX": 0.5,
          "positionPercentY": 0.5,
          "positionType": 1,
          "rotation": 0,
          "scaleX": 1,
          "scaleY": 1,
          "sizePercentX": 0.544791639,
          "sizePercentY": 0.6425926,
          "sizeType": 0,
          "tag": 1000505184,
          "touchAble": true,
          "useMergedTexture": false,
          "visible": true,
          "width": 1046,
          "x": 960,
          "y": 540,
          "capInsetsHeight": 1,
          "capInsetsWidth": 1,
          "capInsetsX": 0,
          "capInsetsY": 0,
          "fileName": null,
          "fileNameData": {
            "path": "res_ui/qyq/common/commonKuang/tanchuangBg.png",
            "plistFile": "",
            "resourceType": 0
          },
          "scale9Enable": false,
          "scale9Height": 694,
          "scale9Width": 1046
        }
      }
    ],
    "options": {
      "__type": "PanelSurrogate:#EditorCommon.JsonModel.Component.GUI",
      "classname": "Panel",
      "name": "mainMask",
      "ZOrder": 0,
      "actiontag": -1,
      "anchorPointX": 0,
      "anchorPointY": 0,
      "classType": "CocoStudio.EngineAdapterWrap.CSPanel",
      "colorB": 255,
      "colorG": 255,
      "colorR": 255,
      "customProperty": "",
      "flipX": false,
      "flipY": false,
      "height": 1080,
      "ignoreSize": false,
      "layoutParameter": null,
      "opacity": 255,
      "positionPercentX": 0,
      "positionPercentY": 0,
      "positionType": 0,
      "rotation": 0,
      "scaleX": 1,
      "scaleY": 1,
      "sizePercentX": 1,
      "sizePercentY": 1,
      "sizeType": 0,
      "tag": 1000505183,
      "touchAble": true,
      "useMergedTexture": false,
      "visible": true,
      "width": 1920,
      "x": 0,
      "y": 0,
      "adaptScreen": false,
      "backGroundImage": null,
      "backGroundImageData": null,
      "backGroundScale9Enable": false,
      "bgColorB": 0,
      "bgColorG": 0,
      "bgColorOpacity": 120,
      "bgColorR": 0,
      "bgEndColorB": 255,
      "bgEndColorG": 200,
      "bgEndColorR": 150,
      "bgStartColorB": 255,
      "bgStartColorG": 255,
      "bgStartColorR": 255,
      "capInsetsHeight": 1,
      "capInsetsWidth": 1,
      "capInsetsX": 0,
      "capInsetsY": 0,
      "clipAble": false,
      "colorType": 1,
      "layoutType": 0,
      "vectorX": 0,
      "vectorY": -0.5
    }
  }
}